eng1014.py
eng1014-0.0.1.dist-info/METADATA
eng1014-0.0.1.dist-info/WHEEL
eng1014-0.0.1.dist-info/top_level.txt
eng1014-0.0.1.dist-info/RECORD
