Metadata-Version: 2.4
Name: eng1014
Version: 0.0.1
Summary: ENG1014 Numerical Methods Module for Monash students
Author-email: Luca Lowndes <Luca@Lowndes.net>
License: MIT
Requires-Python: >=3.8
Requires-Dist: numpy
